boxfs/__init__.py
boxfs/_upath.py
boxfs/boxfs.py
boxfs-0.3.0.dist-info/entry_points.txt
boxfs-0.3.0.dist-info/LICENSE
boxfs-0.3.0.dist-info/METADATA
boxfs-0.3.0.dist-info/WHEEL
boxfs-0.3.0.dist-info/RECORD
