Metadata-Version: 2.1
Name: boxfs
Version: 0.3.0
Summary: Implementation of fsspec for Box file storage
Home-page: https://github.com/IBM/boxfs
License: MIT
Keywords: file-storage,fsspec,file-system,box
Author: Thomas Hunter
Author-email: boxfs.tehunter@gmail.com
Requires-Python: >=3.8,<4.0
Classifier: Development Status :: 2 - Pre-Alpha
Classifier: License :: OSI Approved :: MIT License
Classifier: Programming Language :: Python :: 3
Classifier: Programming Language :: Python :: 3.8
Classifier: Programming Language :: Python :: 3.9
Classifier: Programming Language :: Python :: 3.10
Classifier: Programming Language :: Python :: 3.11
Classifier: Programming Language :: Python :: 3.12
Classifier: Topic :: Database
Classifier: Topic :: Office/Business
Classifier: Topic :: Software Development :: Libraries :: Python Modules
Classifier: Topic :: System :: Filesystems
Classifier: Topic :: Utilities
Provides-Extra: upath
Requires-Dist: boxsdk[jwt] (>=3.7,<4.0)
Requires-Dist: fsspec (>=2023.4)
Requires-Dist: universal-pathlib (>=0.2,<0.3) ; extra == "upath"
Project-URL: Repository, https://github.com/IBM/boxfs
